Workbook

Sheet Cover
B2: HealthCo, Inc.
B3: EchoPilot — AI SaMD for cardiac amyloidosis
B5: Document | C5: Series A Financial Model
B6: Version | C6: v1.0 — Sample
B7: Date | C7: 2026-05-01
B8: Prepared by | C8: STP Advisory — Healthcare Practice
B9: Currency | C9: USD, unless otherwise noted
B10: Fiscal Year | C10: Calendar (Jan-Dec)
B12: Tabs
B13: Summary | C13: KPI dashboard Y1-Y5
B14: Assumptions | C14: All driver inputs
B15: Revenue | C15: Customer build, ASP, channel mix
B16: OpEx | C16: Headcount-driven operating expenses
B17: Cash Flow | C17: Monthly Y1, quarterly Y2-Y3, annual Y4-Y5
B18: Scenarios | C18: Base / Conservative / Upside
B19: Sensitivities | C19: Burn / ASP / Ramp
B22: SAMPLE — FOR DEMONSTRATION ONLY. Not an offer of securities. Not investment advice. All figures illustrative; HealthCo is a fictional company.
B24: Cell color key
B25: Driver / input
B26: Computed (formula)

Sheet Summary
B1: HealthCo — Five-Year Summary
B2: Sample — for demonstration only
B4: KPI | C4: Y1 (2026) | D4: Y2 (2027) | E4: Y3 (2028) | F4: Y4 (2029) | G4: Y5 (2030)
B5: Paying customers (EOY) | C5: =Revenue!C4 | D5: =Revenue!D4 | E5: =Revenue!E4 | F5: =Revenue!F4 | G5: =Revenue!G4
B6: Total echos / yr | C6: =Revenue!C7 | D6: =Revenue!D7 | E6: =Revenue!E7 | F6: =Revenue!F7 | G6: =Revenue!G7
B7: Revenue | C7: =Revenue!C9 | D7: =Revenue!D9 | E7: =Revenue!E9 | F7: =Revenue!F9 | G7: =Revenue!G9
B8: Gross profit | C8: =Revenue!C15 | D8: =Revenue!D15 | E8: =Revenue!E15 | F8: =Revenue!F15 | G8: =Revenue!G15
B9: Gross margin % | C9: =Revenue!C16 | D9: =Revenue!D16 | E9: =Revenue!E16 | F9: =Revenue!F16 | G9: =Revenue!G16
B10: Total OpEx | C10: =OpEx!C30 | D10: =OpEx!D30 | E10: =OpEx!E30 | F10: =OpEx!F30 | G10: =OpEx!G30
B11: EBITDA | C11: =Revenue!C15-OpEx!C30 | D11: =Revenue!D15-OpEx!D30 | E11: =Revenue!E15-OpEx!E30 | F11: =Revenue!F15-OpEx!F30 | G11: =Revenue!G15-OpEx!G30
B12: EBITDA margin % | C12: =C11/Revenue!C9 | D12: =D11/Revenue!D9 | E12: =E11/Revenue!E9 | F12: =F11/Revenue!F9 | G12: =G11/Revenue!G9
B13: Cash at year-end | C13: ='Cash Flow'!N19 | D13: ='Cash Flow'!R19 | E13: ='Cash Flow'!V19 | F13: ='Cash Flow'!W19 | G13: ='Cash Flow'!X19
B14: Annual burn (if EBITDA<0) | C14: =IF(C11<0,-C11,0) | D14: =IF(D11<0,-D11,0) | E14: =IF(E11<0,-E11,0) | F14: =IF(F11<0,-F11,0) | G14: =IF(G11<0,-G11,0)
B15: Runway from year-end (months) | C15: =IF(C14>0,C13/(C14/12),"profitable") | D15: =IF(D14>0,D13/(D14/12),"profitable") | E15: =IF(E14>0,E13/(E14/12),"profitable") | F15: =IF(F14>0,F13/(F14/12),"profitable") | G15: =IF(G14>0,G13/(G14/12),"profitable")

Sheet Assumptions
B1: HealthCo — Driver Assumptions
B3: Driver | C3: Y1 (2026) | D3: Y2 (2027) | E3: Y3 (2028) | F3: Y4 (2029) | G3: Y5 (2030) | H3: Notes
B4: CUSTOMERS & VOLUME
B5: Paying customers (cumulative, end of year) | C5: 10 | D5: 22 | E5: 38 | F5: 58 | G5: 80 | H5: Pilots-to-paid conversion. Comparable: Us2.ai ~30 sites in 2024.
B6: Echos per customer per month (avg) | C6: 180 | D6: 240 | E6: 300 | F6: 340 | G6: 360 | H6: Mid-volume cardiology center: 150-400 echos/mo.
B7: Average Selling Price per study (USD) | C7: 28 | D7: 35 | E7: 45 | F7: 52 | G7: 58 | H7: Ramp from $25 today (pilot pricing) to $58 at scale.
B8: Annual logo churn | C8: 0.05 | D8: 0.07 | E8: 0.08 | F8: 0.09 | G8: 0.1 | H8: Healthcare SaaS benchmark 6-12% logo churn.
B10: CHANNEL MIX (% of new customers)
B11: Direct enterprise | C11: 0.3 | D11: 0.35 | E11: 0.4 | F11: 0.45 | G11: 0.5 | H11: Health-system enterprise contracts.
B12: Channel partner (PACS / OEM) | C12: 0.5 | D12: 0.45 | E12: 0.4 | F12: 0.35 | G12: 0.3 | H12: GE / Philips / Epic-resold; lower ASP, faster reach.
B13: Self-serve / mid-market | C13: 0.2 | D13: 0.2 | E13: 0.2 | F13: 0.2 | G13: 0.2 | H13: Smaller cardiology groups.
B15: HEADCOUNT (FTE, end of year)
B16: Sales & Marketing FTE | C16: 10 | D16: 18 | E16: 26 | F16: 32 | G16: 36 | H16: AE + SDR + clinical specialists + marketing.
B17: R&D / Engineering FTE | C17: 14 | D17: 20 | E17: 26 | F17: 30 | G17: 32 | H17: ML, software, regulatory engineering.
B18: Clinical / Medical Affairs FTE | C18: 3 | D18: 5 | E18: 7 | F18: 8 | G18: 8 | H18: Clinical evidence, KOL, medical affairs.
B19: G&A FTE | C19: 4 | D19: 6 | E19: 8 | F19: 9 | G19: 10 | H19: Finance, ops, legal, people.
B20: Fully-loaded cost per FTE (USD/yr) | C20: 195000 | D20: 205000 | E20: 215000 | F20: 225000 | G20: 235000 | H20: Salary + benefits + payroll tax + equipment.
B22: COGS & MARGIN
B23: Cloud / inference per study (USD) | C23: 0.85 | D23: 0.75 | E23: 0.65 | F23: 0.58 | G23: 0.52 | H23: GPU inference + storage; declines with scale.
B24: Hosting / infra fixed (USD/yr) | C24: 180000 | D24: 240000 | E24: 320000 | F24: 380000 | G24: 420000 | H24: Multi-region HIPAA infra, monitoring.
B25: Customer success cost per customer (USD/yr) | C25: 12000 | D25: 11000 | E25: 10000 | F25: 9500 | G25: 9000 | H25: Implementation + ongoing support.
B27: OTHER OPEX
B28: Clinical study spend (USD/yr) | C28: 800000 | D28: 1200000 | E28: 800000 | F28: 500000 | G28: 400000 | H28: Multi-center post-market studies; tapers post-evidence.
B29: T&E per S&M FTE (USD/yr) | C29: 22000 | D29: 24000 | E29: 26000 | F29: 26000 | G29: 26000 | H29: Conferences (HIMSS, ACC, ESC), customer travel.
B30: Software & tools per FTE (USD/yr) | C30: 4500 | D30: 4500 | E30: 4500 | F30: 4500 | G30: 4500 | H30: Productivity stack, dev tools.
B31: Legal / regulatory (USD/yr) | C31: 350000 | D31: 400000 | E31: 450000 | F31: 500000 | G31: 550000 | H31: Outside counsel, FDA submissions, IP.
B32: Marketing programs (USD/yr) | C32: 600000 | D32: 1100000 | E32: 1600000 | F32: 1900000 | G32: 2100000 | H32: Demand gen, events, content. Excludes S&M payroll.
B34: FINANCING & GRANTS
B35: Series A close (USD) | C35: 15000000 | H35: Closes month 1 of Y1 in this model.
B36: NIH SBIR Phase II (USD, non-dilutive) | C36: 1700000 | H36: Recognized over Y1-Y2 ($850K each).
B37: Starting cash before Series A (USD) | C37: 2200000 | H37: Approx 4.6 months runway at $475K/mo pre-close.

Sheet Revenue
B1: Revenue Build
B3: Driver / Output | C3: Y1 | D3: Y2 | E3: Y3 | F3: Y4 | G3: Y5 | H3: Notes
B4: Paying customers (EOY) | C4: =Assumptions!C5 | D4: =Assumptions!D5 | E4: =Assumptions!E5 | F4: =Assumptions!F5 | G4: =Assumptions!G5
B5: Average customers in year | C5: =(7+C4)/2 | D5: =(C4+D4)/2 | E5: =(D4+E4)/2 | F5: =(E4+F4)/2 | G5: =(F4+G4)/2
B6: Echos per customer per month | C6: =Assumptions!C6 | D6: =Assumptions!D6 | E6: =Assumptions!E6 | F6: =Assumptions!F6 | G6: =Assumptions!G6
B7: Total echos in year | C7: =C5*C6*12 | D7: =D5*D6*12 | E7: =E5*E6*12 | F7: =F5*F6*12 | G7: =G5*G6*12
B8: Average Selling Price per study | C8: =Assumptions!C7 | D8: =Assumptions!D7 | E8: =Assumptions!E7 | F8: =Assumptions!F7 | G8: =Assumptions!G7
B9: Gross revenue (echos x ASP) | C9: =C7*C8 | D9: =D7*D8 | E9: =E7*E8 | F9: =F7*F8 | G9: =G7*G8
B11: COGS — variable (cloud per study) | C11: =C7*Assumptions!C23 | D11: =D7*Assumptions!D23 | E11: =E7*Assumptions!E23 | F11: =F7*Assumptions!F23 | G11: =G7*Assumptions!G23
B12: COGS — hosting fixed | C12: =Assumptions!C24 | D12: =Assumptions!D24 | E12: =Assumptions!E24 | F12: =Assumptions!F24 | G12: =Assumptions!G24
B13: COGS — customer success | C13: =C5*Assumptions!C25 | D13: =D5*Assumptions!D25 | E13: =E5*Assumptions!E25 | F13: =F5*Assumptions!F25 | G13: =G5*Assumptions!G25
B14: Total COGS | C14: =SUM(C11:C13) | D14: =SUM(D11:D13) | E14: =SUM(E11:E13) | F14: =SUM(F11:F13) | G14: =SUM(G11:G13)
B15: Gross profit | C15: =C9-C14 | D15: =D9-D14 | E15: =E9-E14 | F15: =F9-F14 | G15: =G9-G14
B16: Gross margin % | C16: =C15/C9 | D16: =D15/D9 | E16: =E15/E9 | F16: =F15/F9 | G16: =G15/G9

Sheet OpEx
B1: Operating Expenses
B3: Driver / Output | C3: Y1 | D3: Y2 | E3: Y3 | F3: Y4 | G3: Y5 | H3: Notes
B4: S&M FTE | C4: =Assumptions!C16 | D4: =Assumptions!D16 | E4: =Assumptions!E16 | F4: =Assumptions!F16 | G4: =Assumptions!G16
B5: R&D FTE | C5: =Assumptions!C17 | D5: =Assumptions!D17 | E5: =Assumptions!E17 | F5: =Assumptions!F17 | G5: =Assumptions!G17
B6: Clinical FTE | C6: =Assumptions!C18 | D6: =Assumptions!D18 | E6: =Assumptions!E18 | F6: =Assumptions!F18 | G6: =Assumptions!G18
B7: G&A FTE | C7: =Assumptions!C19 | D7: =Assumptions!D19 | E7: =Assumptions!E19 | F7: =Assumptions!F19 | G7: =Assumptions!G19
B8: Total FTE | C8: =C4+C5+C6+C7 | D8: =D4+D5+D6+D7 | E8: =E4+E5+E6+E7 | F8: =F4+F5+F6+F7 | G8: =G4+G5+G6+G7
B9: Avg S&M FTE | C9: =(6+C4)/2 | D9: =(C4+D4)/2 | E9: =(D4+E4)/2 | F9: =(E4+F4)/2 | G9: =(F4+G4)/2
B10: Avg R&D FTE | C10: =(10+C5)/2 | D10: =(C5+D5)/2 | E10: =(D5+E5)/2 | F10: =(E5+F5)/2 | G10: =(F5+G5)/2
B11: Avg Clinical FTE | C11: =(2+C6)/2 | D11: =(C6+D6)/2 | E11: =(D6+E6)/2 | F11: =(E6+F6)/2 | G11: =(F6+G6)/2
B12: Avg G&A FTE | C12: =(4+C7)/2 | D12: =(C7+D7)/2 | E12: =(D7+E7)/2 | F12: =(E7+F7)/2 | G12: =(F7+G7)/2
B13: Fully-loaded cost per FTE | C13: =Assumptions!C20 | D13: =Assumptions!D20 | E13: =Assumptions!E20 | F13: =Assumptions!F20 | G13: =Assumptions!G20
B15: Payroll — S&M | C15: =C9*C13 | D15: =D9*D13 | E15: =E9*E13 | F15: =F9*F13 | G15: =G9*G13
B16: Payroll — R&D | C16: =C10*C13 | D16: =D10*D13 | E16: =E10*E13 | F16: =F10*F13 | G16: =G10*G13
B17: Payroll — Clinical | C17: =C11*C13 | D17: =D11*D13 | E17: =E11*E13 | F17: =F11*F13 | G17: =G11*G13
B18: Payroll — G&A | C18: =C12*C13 | D18: =D12*D13 | E18: =E12*E13 | F18: =F12*F13 | G18: =G12*G13
B20: T&E (S&M) | C20: =C9*Assumptions!C29 | D20: =D9*Assumptions!D29 | E20: =E9*Assumptions!E29 | F20: =F9*Assumptions!F29 | G20: =G9*Assumptions!G29
B21: Software & tools (all FTE) | C21: =C8*Assumptions!C30 | D21: =D8*Assumptions!D30 | E21: =E8*Assumptions!E30 | F21: =F8*Assumptions!F30 | G21: =G8*Assumptions!G30
B22: Marketing programs | C22: =Assumptions!C32 | D22: =Assumptions!D32 | E22: =Assumptions!E32 | F22: =Assumptions!F32 | G22: =Assumptions!G32
B23: Clinical study spend | C23: =Assumptions!C28 | D23: =Assumptions!D28 | E23: =Assumptions!E28 | F23: =Assumptions!F28 | G23: =Assumptions!G28
B24: Legal / regulatory | C24: =Assumptions!C31 | D24: =Assumptions!D31 | E24: =Assumptions!E31 | F24: =Assumptions!F31 | G24: =Assumptions!G31
B26: S&M total | C26: =C15+C20+C22 | D26: =D15+D20+D22 | E26: =E15+E20+E22 | F26: =F15+F20+F22 | G26: =G15+G20+G22
B27: R&D total | C27: =C16 | D27: =D16 | E27: =E16 | F27: =F16 | G27: =G16
B28: Clinical total | C28: =C17+C23 | D28: =D17+D23 | E28: =E17+E23 | F28: =F17+F23 | G28: =G17+G23
B29: G&A total | C29: =C18+C24+C21 | D29: =D18+D24+D21 | E29: =E18+E24+E21 | F29: =F18+F24+F21 | G29: =G18+G24+G21
B30: Total OpEx | C30: =C26+C27+C28+C29 | D30: =D26+D27+D28+D29 | E30: =E26+E27+E28+E29 | F30: =F26+F27+F28+F29 | G30: =G26+G27+G28+G29

Sheet Cash Flow
B1: Cash Flow — Monthly Y1, Quarterly Y2-Y3, Annual Y4-Y5
C3: Y1 | D3: Y1 | E3: Y1 | F3: Y1 | G3: Y1 | H3: Y1 | I3: Y1 | J3: Y1 | K3: Y1 | L3: Y1 | M3: Y1 | N3: Y1 | O3: Y2 | P3: Y2 | Q3: Y2 | R3: Y2 | S3: Y3 | T3: Y3 | U3: Y3 | V3: Y3 | W3: Y4 | X3: Y5
C4: M1 | D4: M2 | E4: M3 | F4: M4 | G4: M5 | H4: M6 | I4: M7 | J4: M8 | K4: M9 | L4: M10 | M4: M11 | N4: M12 | O4: Q1 | P4: Q2 | Q4: Q3 | R4: Q4 | S4: Q1 | T4: Q2 | U4: Q3 | V4: Q4 | W4: FY | X4: FY
B5: Revenue | C5: =Revenue!C9*0.08333333333333333 | D5: =Revenue!C9*0.08333333333333333 | E5: =Revenue!C9*0.08333333333333333 | F5: =Revenue!C9*0.08333333333333333 | G5: =Revenue!C9*0.08333333333333333 | H5: =Revenue!C9*0.08333333333333333 | I5: =Revenue!C9*0.08333333333333333 | J5: =Revenue!C9*0.08333333333333333 | K5: =Revenue!C9*0.08333333333333333 | L5: =Revenue!C9*0.08333333333333333 | M5: =Revenue!C9*0.08333333333333333 | N5: =Revenue!C9*0.08333333333333333 | O5: =Revenue!D9*0.25 | P5: =Revenue!D9*0.25 | Q5: =Revenue!D9*0.25 | R5: =Revenue!D9*0.25 | S5: =Revenue!E9*0.25 | T5: =Revenue!E9*0.25 | U5: =Revenue!E9*0.25 | V5: =Revenue!E9*0.25 | W5: =Revenue!F9*1.0 | X5: =Revenue!G9*1.0
B6: COGS | C6: =Revenue!C14*0.08333333333333333 | D6: =Revenue!C14*0.08333333333333333 | E6: =Revenue!C14*0.08333333333333333 | F6: =Revenue!C14*0.08333333333333333 | G6: =Revenue!C14*0.08333333333333333 | H6: =Revenue!C14*0.08333333333333333 | I6: =Revenue!C14*0.08333333333333333 | J6: =Revenue!C14*0.08333333333333333 | K6: =Revenue!C14*0.08333333333333333 | L6: =Revenue!C14*0.08333333333333333 | M6: =Revenue!C14*0.08333333333333333 | N6: =Revenue!C14*0.08333333333333333 | O6: =Revenue!D14*0.25 | P6: =Revenue!D14*0.25 | Q6: =Revenue!D14*0.25 | R6: =Revenue!D14*0.25 | S6: =Revenue!E14*0.25 | T6: =Revenue!E14*0.25 | U6: =Revenue!E14*0.25 | V6: =Revenue!E14*0.25 | W6: =Revenue!F14*1.0 | X6: =Revenue!G14*1.0
B7: Gross profit | C7: =C5-C6 | D7: =D5-D6 | E7: =E5-E6 | F7: =F5-F6 | G7: =G5-G6 | H7: =H5-H6 | I7: =I5-I6 | J7: =J5-J6 | ... X7: =X5-X6
B8: OpEx — S&M | C8: =OpEx!C26*0.08333333333333333 | D8: =OpEx!C26*0.08333333333333333 | E8: =OpEx!C26*0.08333333333333333 | F8: =OpEx!C26*0.08333333333333333 | G8: =OpEx!C26*0.08333333333333333 | H8: =OpEx!C26*0.08333333333333333 | I8: =OpEx!C26*0.08333333333333333 | J8: =OpEx!C26*0.08333333333333333 | K8: =OpEx!C26*0.08333333333333333 | L8: =OpEx!C26*0.08333333333333333 | M8: =OpEx!C26*0.08333333333333333 | N8: =OpEx!C26*0.08333333333333333 | O8: =OpEx!D26*0.25 | P8: =OpEx!D26*0.25 | Q8: =OpEx!D26*0.25 | R8: =OpEx!D26*0.25 | S8: =OpEx!E26*0.25 | T8: =OpEx!E26*0.25 | U8: =OpEx!E26*0.25 | V8: =OpEx!E26*0.25 | W8: =OpEx!F26*1.0 | X8: =OpEx!G26*1.0
B9: OpEx — R&D | C9: =OpEx!C27*0.08333333333333333 | D9: =OpEx!C27*0.08333333333333333 | E9: =OpEx!C27*0.08333333333333333 | F9: =OpEx!C27*0.08333333333333333 | G9: =OpEx!C27*0.08333333333333333 | H9: =OpEx!C27*0.08333333333333333 | I9: =OpEx!C27*0.08333333333333333 | J9: =OpEx!C27*0.08333333333333333 | K9: =OpEx!C27*0.08333333333333333 | L9: =OpEx!C27*0.08333333333333333 | M9: =OpEx!C27*0.08333333333333333 | N9: =OpEx!C27*0.08333333333333333 | O9: =OpEx!D27*0.25 | P9: =OpEx!D27*0.25 | Q9: =OpEx!D27*0.25 | R9: =OpEx!D27*0.25 | S9: =OpEx!E27*0.25 | T9: =OpEx!E27*0.25 | U9: =OpEx!E27*0.25 | V9: =OpEx!E27*0.25 | W9: =OpEx!F27*1.0 | X9: =OpEx!G27*1.0
B10: OpEx — Clinical | C10: =OpEx!C28*0.08333333333333333 | D10: =OpEx!C28*0.08333333333333333 | E10: =OpEx!C28*0.08333333333333333 | F10: =OpEx!C28*0.08333333333333333 | G10: =OpEx!C28*0.08333333333333333 | H10: =OpEx!C28*0.08333333333333333 | I10: =OpEx!C28*0.08333333333333333 | J10: =OpEx!C28*0.08333333333333333 | K10: =OpEx!C28*0.08333333333333333 | L10: =OpEx!C28*0.08333333333333333 | M10: =OpEx!C28*0.08333333333333333 | N10: =OpEx!C28*0.08333333333333333 | O10: =OpEx!D28*0.25 | P10: =OpEx!D28*0.25 | Q10: =OpEx!D28*0.25 | R10: =OpEx!D28*0.25 | S10: =OpEx!E28*0.25 | T10: =OpEx!E28*0.25 | U10: =OpEx!E28*0.25 | V10: =OpEx!E28*0.25 | W10: =OpEx!F28*1.0 | X10: =OpEx!G28*1.0
B11: OpEx — G&A | C11: =OpEx!C29*0.08333333333333333 | D11: =OpEx!C29*0.08333333333333333 | E11: =OpEx!C29*0.08333333333333333 | F11: =OpEx!C29*0.08333333333333333 | G11: =OpEx!C29*0.08333333333333333 | H11: =OpEx!C29*0.08333333333333333 | I11: =OpEx!C29*0.08333333333333333 | J11: =OpEx!C29*0.08333333333333333 | K11: =OpEx!C29*0.08333333333333333 | L11: =OpEx!C29*0.08333333333333333 | M11: =OpEx!C29*0.08333333333333333 | N11: =OpEx!C29*0.08333333333333333 | O11: =OpEx!D29*0.25 | P11: =OpEx!D29*0.25 | Q11: =OpEx!D29*0.25 | R11: =OpEx!D29*0.25 | S11: =OpEx!E29*0.25 | T11: =OpEx!E29*0.25 | U11: =OpEx!E29*0.25 | V11: =OpEx!E29*0.25 | W11: =OpEx!F29*1.0 | X11: =OpEx!G29*1.0
B12: Total OpEx | C12: =SUM(C8:C11) | D12: =SUM(D8:D11) | E12: =SUM(E8:E11) | F12: =SUM(F8:F11) | G12: =SUM(G8:G11) | H12: =SUM(H8:H11) | I12: =SUM(I8:I11) | J12: =SUM(J8:J11) | ... X12: =SUM(X8:X11)
B13: EBITDA | C13: =C7-C12 | D13: =D7-D12 | E13: =E7-E12 | F13: =F7-F12 | G13: =G7-G12 | H13: =H7-H12 | I13: =I7-I12 | J13: =J7-J12 | ... X13: =X7-X12
B15: Series A inflow | C15: =Assumptions!C35 | D15: 0 | E15: 0 | F15: 0 | G15: 0 | H15: 0 | I15: 0 | J15: 0 | K15: 0 | L15: 0 | M15: 0 | N15: 0 | O15: 0 | P15: 0 | Q15: 0 | R15: 0 | S15: 0 | T15: 0 | U15: 0 | V15: 0 | W15: 0 | X15: 0
B16: SBIR grant inflow | C16: =Assumptions!C36/2*0.08333333333333333 | D16: =Assumptions!C36/2*0.08333333333333333 | E16: =Assumptions!C36/2*0.08333333333333333 | F16: =Assumptions!C36/2*0.08333333333333333 | G16: =Assumptions!C36/2*0.08333333333333333 | H16: =Assumptions!C36/2*0.08333333333333333 | I16: =Assumptions!C36/2*0.08333333333333333 | J16: =Assumptions!C36/2*0.08333333333333333 | K16: =Assumptions!C36/2*0.08333333333333333 | L16: =Assumptions!C36/2*0.08333333333333333 | M16: =Assumptions!C36/2*0.08333333333333333 | N16: =Assumptions!C36/2*0.08333333333333333 | O16: =Assumptions!C36/2*0.25 | P16: =Assumptions!C36/2*0.25 | Q16: =Assumptions!C36/2*0.25 | R16: =Assumptions!C36/2*0.25 | S16: 0 | T16: 0 | U16: 0 | V16: 0 | W16: 0 | X16: 0
B17: Net cash flow | C17: =C13+C15+C16 | D17: =D13+D15+D16 | E17: =E13+E15+E16 | F17: =F13+F15+F16 | G17: =G13+G15+G16 | H17: =H13+H15+H16 | I17: =I13+I15+I16 | J17: =J13+J15+J16 | ... X17: =X13+X15+X16
B18: Beginning cash | C18: =Assumptions!C37 | D18: =C19 | E18: =D19 | F18: =E19 | G18: =F19 | H18: =G19 | I18: =H19 | J18: =I19 | K18: =J19 | ... X18: =W19
B19: Ending cash | C19: =C18+C17 | D19: =D18+D17 | E19: =E18+E17 | F19: =F18+F17 | G19: =G18+G17 | H19: =H18+H17 | I19: =I18+I17 | J19: =J18+J17 | ... X19: =X18+X17

Sheet Scenarios
B1: Scenario Toggles — Base / Conservative / Upside
B2: Read-only view: scenarios are presented as factor adjustments to base drivers. Use Sensitivities tab for ±20% / ±30% sweeps.
B4: Driver | C4: Conservative | D4: Base | E4: Upside | F4: Notes
B5: Customer ramp factor (vs. Base) | C5: 0.7 | D5: 1 | E5: 1.3 | F5: Conservative reflects slower hospital procurement; upside reflects channel partner uplift.
B6: ASP factor (vs. Base) | C6: 0.85 | D6: 1 | E6: 1.15 | F6: Reimbursement (CPT III code timing) is the swing factor.
B7: Echos per customer factor | C7: 0.85 | D7: 1 | E7: 1.15 | F7: Health-system penetration depth.
B8: Churn (absolute %) | C8: 0.12 | D8: 0.08 | E8: 0.05 | F8: Conservative assumes one large logo loss in Y2-Y3.
B9: OpEx ramp factor | C9: 1.1 | D9: 1 | E9: 0.95 | F9: Conservative assumes longer sales cycles requiring more headcount.
B11: Implied Y3 revenue (illustrative)
B12: Conservative | C12: =Revenue!E10*C5*C6*C7 | D12: (formula references Revenue tab Y3 revenue scaled by factors)
B13: Base | C13: =Revenue!E10*D5*D6*D7
B14: Upside | C14: =Revenue!E10*E5*E6*E7

Sheet Sensitivities
B1: Sensitivities — Y3 Revenue & EBITDA
B4: Sweep | C4: -20% / -30% | D4: -10% / -15% | E4: Base | F4: +10% / +15% | G4: +20% / +30% | H4: Notes
B5: ASP factor | C5: 0.8 | D5: 0.9 | E5: 1 | F5: 1.1 | G5: 1.2 | H5: Direct lever on revenue.
B6: Y3 Revenue at sensitivity | C6: =Revenue!E10*C5 | D6: =Revenue!E10*D5 | E6: =Revenue!E10*E5 | F6: =Revenue!E10*F5 | G6: =Revenue!E10*G5
B8: Customer ramp factor | C8: 0.7 | D8: 0.85 | E8: 1 | F8: 1.15 | G8: 1.3 | H8: Customer count (and thus echo volume) scaling.
B9: Y3 Revenue at sensitivity | C9: =Revenue!E10*C8 | D9: =Revenue!E10*D8 | E9: =Revenue!E10*E8 | F9: =Revenue!E10*F8 | G9: =Revenue!E10*G8
B11: Burn factor | C11: 0.8 | D11: 0.9 | E11: 1 | F11: 1.1 | G11: 1.2 | H11: Applied to Total OpEx.
B12: Y3 OpEx at sensitivity | C12: =INDEX(OpEx!E:E,MATCH("Total OpEx",OpEx!B:B,0))*C11 | D12: =INDEX(OpEx!E:E,MATCH("Total OpEx",OpEx!B:B,0))*D11 | E12: =INDEX(OpEx!E:E,MATCH("Total OpEx",OpEx!B:B,0))*E11 | F12: =INDEX(OpEx!E:E,MATCH("Total OpEx",OpEx!B:B,0))*F11 | G12: =INDEX(OpEx!E:E,MATCH("Total OpEx",OpEx!B:B,0))*G11
B13: Implied Y3 EBITDA | C13: =Revenue!E10-INDEX(Revenue!E:E,MATCH("Total COGS",Revenue!B:B,0))-C12 | D13: =Revenue!E10-INDEX(Revenue!E:E,MATCH("Total COGS",Revenue!B:B,0))-D12 | E13: =Revenue!E10-INDEX(Revenue!E:E,MATCH("Total COGS",Revenue!B:B,0))-E12 | F13: =Revenue!E10-INDEX(Revenue!E:E,MATCH("Total COGS",Revenue!B:B,0))-F12 | G13: =Revenue!E10-INDEX(Revenue!E:E,MATCH("Total COGS",Revenue!B:B,0))-G12
