Workbook

Sheet Cover
B2: HealthCo, Inc. — Pro Forma Cap Table
B3: Series A Round
B5: Round size | C5: $15.0M at $50.0M pre / $65.0M post
B6: Option pool top-up | C6: To 12% of post-money fully diluted (lead's ask)
B7: SAFEs | C7: Two YC post-money SAFEs; convert at lower of cap or this-round price
B9: SAMPLE — FOR DEMONSTRATION ONLY. Not a securities offering. Numbers are illustrative.

Sheet Current Cap Table
B1: Current Cap Table — Pre-Series A (Fully Diluted)
B3: Holder / Class | C3: Type | D3: Shares | E3: % FD | F3: Notes
B4: Maya Chen — CEO | C4: Common | D4: 3492063 | E4: =D4/D$9
B5: Raj Iyer — CTO | C5: Common | D5: 2857143 | E5: =D5/D$9
B6: Sarah Whittaker — CMO | C6: Common | D6: 1269841 | E6: =D6/D$9
B7: Option pool — granted | C7: Options | D7: 1587302 | E7: =D7/D$9
B8: Option pool — available | C8: Options | D8: 793651 | E8: =D8/D$9
B9: Total pre-SAFE shares (base) | D9: =SUM(D4:D8)
B11: SAFE 1 — Angel round (Q3 2022) | C11: SAFE | E11: $1.5M @ $10M post-money cap; converts at Series A
B12: SAFE 2 — Angel extension (Q1 2023) | C12: SAFE | E12: $1.0M @ $18M post-money cap; converts at Series A
B14: NIH SBIR Phase II grant | E14: $1.7M non-dilutive — does not appear on cap table

Sheet SAFE Conversion Math
B1: SAFE Conversion — at Series A
B2: Standard YC post-money SAFE: cap-only, no discount, no MFN. Converts at lower of (post-money valuation cap) or (Series A price per share).
B4: Item | C4: SAFE 1 | D4: SAFE 2 | E4: Notes
B5: Investment ($) | C5: 1500000 | D5: 1000000
B6: Post-money cap ($) | C6: 10000000 | D6: 18000000
B7: Discount % | C7: 0 | D7: 0
B8: Series A pre-money ($) | C8: 50000000
B9: Series A investment ($) | C9: 15000000
B10: Series A post-money ($) | C10: =C8+C9
B12: SAFE ownership % (= investment / cap) | C12: =C5/C6 | D12: =D5/D6 | E12: Post-money SAFE: ownership baked into cap.
B13: Implied SAFE price-per-share | C13: =C6/'Current Cap Table'!D9 | D13: =D6/'Current Cap Table'!D9 | E13: Cap divided by pre-SAFE base shares.
B14: Series A price-per-share (pre-money / pre-FD) | C14: =C8/'Current Cap Table'!D9 | E14: Standard convention: pre-money / pre-money FD.
B15: Conversion price (lower of) | C15: =MIN(C13,C14) | D15: =MIN(D13,C14)
B16: Shares issued at conversion | C16: =C5/C15 | D16: =D5/D15

Sheet Series A Pro Forma — Base
B1: Series A Pro Forma — Base ($50M pre / $15M / $65M post, 12% pool)
B3: Holder / Class | C3: Stage | D3: Shares | E3: % FD | F3: Notes
B4: Maya Chen — CEO | C4: Common | D4: 3492063
B5: Raj Iyer — CTO | C5: Common | D5: 2857143
B6: Sarah Whittaker — CMO | C6: Common | D6: 1269841
B7: Option pool — granted (pre-A) | C7: Options | D7: 1587302
B8: Option pool — available (pre-A) | C8: Options | D8: 793651
B9: Subtotal: pre-A base shares | D9: =SUM(D4:D8)
B11: SAFE 1 (converted) | C11: Pref | D11: ='SAFE Conversion Math'!C16 | F11: $1.5M @ $10M cap
B12: SAFE 2 (converted) | C12: Pref | D12: ='SAFE Conversion Math'!D16 | F12: $1.0M @ $18M cap
B15: Round inputs
B16: Pre-money ($) | D16: 50000000
B17: Investment ($) | D17: 15000000
B18: Post-money ($) | D18: =D16+D17
B19: Target option pool % (post-money FD) | D19: 0.12
B20: SAFE 1 ownership % (post-money) | D20: ='SAFE Conversion Math'!C12
B21: SAFE 2 ownership % (post-money) | D21: ='SAFE Conversion Math'!D12
B22: New investor % (post-money) | D22: =D17/D18
B23: Founders + existing common % (post-money) | D23: =1-D19-D20-D21-D22
B24: Founders + existing common shares (carried) | D24: =D4+D5+D6+D7
B25: Total post-money shares | D25: =D24/D23
B26: New option pool (top-up to 12%) | D26: =D25*D19
B27: Series A new investor shares | D27: =D25*D22
B28: SAFE 1 shares (re-stated for total) | D28: =D25*D20
B29: SAFE 2 shares (re-stated for total) | D29: =D25*D21
B31: POST-MONEY CAP TABLE
B32: Holder | C32: Type | D32: Shares | E32: % FD | F32: Notes
B33: Maya Chen — Common | C33: Common | D33: =D4 | E33: =D33/D$25
B34: Raj Iyer — Common | C34: Common | D34: =D5 | E34: =D34/D$25
B35: Sarah Whittaker — Common | C35: Common | D35: =D6 | E35: =D35/D$25
B36: Existing options (granted, carried) | C36: Options | D36: =D7 | E36: =D36/D$25
B37: Option pool — refreshed to 12% | C37: Options | D37: =D25*D19-D7 | E37: =(D25*D19-D7)/D$25
B38: SAFE 1 — converted Pref | C38: Pref | D38: =D25*D20 | E38: =D20
B39: SAFE 2 — converted Pref | C39: Pref | D39: =D25*D21 | E39: =D21
B40: Series A — new investor | C40: Series A Pref | D40: =D27 | E40: =D22
B41: TOTAL | D41: =SUM(D33:D40) | E41: =SUM(E33:E40)

Sheet Scenarios
B1: Series A Pro Forma — Scenarios
B3: Item | C3: Low ($40M pre) | D3: Base ($50M pre) | E3: High ($60M pre) | F3: Lead Pushback (15% pool) | G3: Notes
B4: Pre-money ($) | C4: 40000000 | D4: 50000000 | E4: 60000000 | F4: 50000000
B5: Investment ($) | C5: 15000000 | D5: 15000000 | E5: 15000000 | F5: 15000000
B6: Post-money ($) | C6: =C4+C5 | D6: =D4+D5 | E6: =E4+E5 | F6: =F4+F5
B7: Target pool % (post-money) | C7: 0.12 | D7: 0.12 | E7: 0.12 | F7: 0.15
B9: SAFE 1 % (= 1.5 / 10) | C9: =1500000/10000000 | D9: =1500000/10000000 | E9: =1500000/10000000 | F9: =1500000/10000000
B10: SAFE 2 % (= 1.0 / 18) | C10: =1000000/18000000 | D10: =1000000/18000000 | E10: =1000000/18000000 | F10: =1000000/18000000
B11: New investor % (= inv / post) | C11: =C5/C6 | D11: =D5/D6 | E11: =E5/E6 | F11: =F5/F6
B12: Founders + existing common % (residual) | C12: =1-C7-C9-C10-C11 | D12: =1-D7-D9-D10-D11 | E12: =1-E7-E9-E10-E11 | F12: =1-F7-F9-F10-F11
B14: Founder ownership only (Maya+Raj+Sarah) | C14: =C12*48/58 | D14: =D12*48/58 | E14: =E12*48/58 | F14: =F12*48/58
B15: Maya (22% of pre-A common) | C15: =C12*22/58 | D15: =D12*22/58 | E15: =E12*22/58 | F15: =F12*22/58
B16: Raj (18%) | C16: =C12*18/58 | D16: =D12*18/58 | E16: =E12*18/58 | F16: =F12*18/58
B17: Sarah (8%) | C17: =C12*8/58 | D17: =D12*8/58 | E17: =E12*8/58 | F17: =F12*8/58
B19: Sanity: total % must = 100% | C19: =C7+C9+C10+C11+C12 | D19: =D7+D9+D10+D11+D12 | E19: =E7+E9+E10+E11+E12 | F19: =F7+F9+F10+F11+F12

Sheet Founder Trajectory
B1: Founder Ownership Trajectory
B2: Pre-A → Series A → Series B (assumed) → Exit
B4: Founder | C4: Pre-Series-A | D4: Post-Series-A | E4: Post-Series-B | F4: At Exit ($500M)
B5: Maya Chen | C5: 0.22 | D5: =Scenarios!D12*0.22/0.58 | E5: =D5*0.77 | F5: =E5
B6: Raj Iyer | C6: 0.18 | D6: =Scenarios!D12*0.18/0.58 | E6: =D6*0.77 | F6: =E6
B7: Sarah Whittaker | C7: 0.08 | D7: =Scenarios!D12*0.08/0.58 | E7: =D7*0.77 | F7: =E7
B9: Series B assumptions
B10: Pre-money | C10: 120000000
B11: Raise | C11: 30000000
B12: Post-money | C12: =C32+C33
B13: New-investor % | C13: =C33/C34
B14: Pool top-up % (incremental) | C14: 0.03
B15: Other-holder retention factor | C15: =1-C35-C36
B17: Exit assumptions
B18: Acquisition price | C18: 500000000
B19: Maya proceeds (gross, pre-tax, pre-pref) | C19: =C18*F5
B20: Raj proceeds | C20: =C18*F6
B21: Sarah proceeds | C21: =C18*F7
B22: Note: simplified — does not model liquidation preferences (1x non-participating assumed for clean common math).

Sheet Dead Equity Flag
B1: Dead Equity Analysis
B2: Surfaces non-active holders >2% post-money. HealthCo is intentionally clean — all founders are active executives. Logic is reproducible for other deals.
B4: Holder | C4: Active? | D4: Post-A % | E4: Threshold | F4: Flag | G4: Notes
B5: Maya Chen | C5: Yes | D5: ='Founder Trajectory'!D5 | E5: 0.02 | F5: =IF(AND(C5="No",D5>E5),"FLAG: dead equity",IF(C5="N/A","n/a (investor)","OK")) | G5: Founder, CEO, full-time
B6: Raj Iyer | C6: Yes | D6: ='Founder Trajectory'!D6 | E6: 0.02 | F6: =IF(AND(C6="No",D6>E6),"FLAG: dead equity",IF(C6="N/A","n/a (investor)","OK")) | G6: Founder, CTO, full-time
B7: Sarah Whittaker | C7: Yes | D7: ='Founder Trajectory'!D7 | E7: 0.02 | F7: =IF(AND(C7="No",D7>E7),"FLAG: dead equity",IF(C7="N/A","n/a (investor)","OK")) | G7: Founder, CMO, full-time
B8: SAFE 1 holders (angel syndicate) | C8: N/A | D8: =Scenarios!D9 | E8: 0.02 | F8: =IF(AND(C8="No",D8>E8),"FLAG: dead equity",IF(C8="N/A","n/a (investor)","OK")) | G8: Investors — exempt from dead-equity test
B9: SAFE 2 holders (angel syndicate) | C9: N/A | D9: =Scenarios!D10 | E9: 0.02 | F9: =IF(AND(C9="No",D9>E9),"FLAG: dead equity",IF(C9="N/A","n/a (investor)","OK")) | G9: Investors — exempt from dead-equity test
B11: Logic
B12: Flag = (Active='No') AND (Post-A % > 2%)
B13: Investor holders (SAFEs, Series A) are exempt — passive capital is expected.
